whatdiditdo/README.MD
whatdiditdo/__init__.py
whatdiditdo/requirements.txt
whatdiditdo/thirdparty.json
whatdiditdo-0.10.dist-info/LICENSE.rst
whatdiditdo-0.10.dist-info/METADATA
whatdiditdo-0.10.dist-info/WHEEL
whatdiditdo-0.10.dist-info/top_level.txt
whatdiditdo-0.10.dist-info/RECORD
