Metadata-Version: 2.1
Name: whatdiditdo
Version: 0.10
Summary: Observes what processes are doing (Windows only)
Home-page: https://github.com/hansalemaos/whatdiditdo
Author: Johannes Fischer
Author-email: aulasparticularesdealemaosp@gmail.com
License: MIT
Keywords: Monitoring,processes
Classifier: Development Status :: 4 - Beta
Classifier: Programming Language :: Python :: 3 :: Only
Classifier: Programming Language :: Python :: 3.10
Classifier: Topic :: Software Development :: Libraries :: Python Modules
Classifier: Topic :: Utilities
License-File: LICENSE.rst
Requires-Dist: a-pandas-ex-apply-ignore-exceptions
Requires-Dist: a-pandas-ex-df-to-string
Requires-Dist: a-pandas-ex-fast-string
Requires-Dist: a-pandas-ex-horizontal-explode
Requires-Dist: copytool
Requires-Dist: flatten-everything
Requires-Dist: gethandledf
Requires-Dist: getregdf
Requires-Dist: kthread-sleep
Requires-Dist: list-all-files-recursively
Requires-Dist: numpy
Requires-Dist: pandas
Requires-Dist: psutil
Requires-Dist: subprocesskiller
Requires-Dist: touchtouch
